coexist/__init__.py
coexist/__version__.py
coexist/access.py
coexist/async_coexist_error.py
coexist/ballistics.py
coexist/base.py
coexist/code_trees.py
coexist/combiners.py
coexist/liggghts.py
coexist/optimisation.py
coexist/plots.py
coexist/schedulers.py
coexist/template_access_script.py
coexist/utilities.py
coexist-0.3.2.dist-info/LICENSE
coexist-0.3.2.dist-info/METADATA
coexist-0.3.2.dist-info/WHEEL
coexist-0.3.2.dist-info/top_level.txt
coexist-0.3.2.dist-info/RECORD
